  {
    "header":[{
      "left": [
        {
          "type": "image",
          "url": "/asset/image/logo.png"
        },
        {
          "type": "link",
          "content": [
            {
              "label": "About Us",
              "url": "header"
            },
            {
              "label": "Admissins",
              "url":"header"
            },
            {
              "label":"Boarding",
              "url":"header"
            },
            {
              "label":"Contact Us",
              "url":"header"
            }
          ]
        }
      ],
      "right": [
        {
          "type": "link",
          "content":[
            {
              "label": "Culford Post",
              "url": "#"
            },
            {
              "label": "Email",
              "url": "#"
            },
            {
              "label": ""
            }
          ]
        },
        {
          "type": "icon",
          "content":[
            {
              "address": "#",
              "icon":"facebook"
            },
            {
              "address":"#",
              "icon":"twitter"
            }
          ]
        }
      ]
    }
  ],
  "lpMenu":[
    {
      "label": "Welcome from the Head",
      "url": "#"
    },
    {
      "label": "Life at Culfort",
      "url": "#"
    },
    {
      "label": "Latest news",
      "url": "#"
    },
    {
      "label": "Request a prospectus",
      "url": "#"
    }
  ]
}
  
